wenxue_mcp_tools_service/__init__.py
wenxue_mcp_tools_service/config.py
wenxue_mcp_tools_service/server.py
wenxue_mcp_tools_service/storage.py
wenxue_mcp_tools_service/utils.py
wenxue_mcp_tools_service-0.1.1.dist-info/METADATA
wenxue_mcp_tools_service-0.1.1.dist-info/WHEEL
wenxue_mcp_tools_service-0.1.1.dist-info/entry_points.txt
wenxue_mcp_tools_service-0.1.1.dist-info/top_level.txt
wenxue_mcp_tools_service-0.1.1.dist-info/RECORD
