Metadata-Version: 2.4
Name: wenxue-mcp-tools-service
Version: 0.1.1
Summary: 问学平台所有涉及到的MCP小工具服务合集
Requires-Python: >=3.12
Requires-Dist: mcp[cli]>=1.12.4
Requires-Dist: pillow>=11.3.0
Requires-Dist: pymupdf>=1.26.3
Requires-Dist: requests>=2.32.4
Requires-Dist: cos-python-sdk-v5>=1.9.38
Requires-Dist: pymysql>=1.1.1
Requires-Dist: pandas>=2.3.1
